LICENSE
MANIFEST.in
README.md
setup.py
apimaticcalculatorpythonv2/__init__.py
apimaticcalculatorpythonv2/api_helper.py
apimaticcalculatorpythonv2/apimaticcalculatorpythonv2_client.py
apimaticcalculatorpythonv2/configuration.py
apimaticcalculatorpythonv2/decorators.py
apimaticcalculatorpythonv2.egg-info/PKG-INFO
apimaticcalculatorpythonv2.egg-info/SOURCES.txt
apimaticcalculatorpythonv2.egg-info/dependency_links.txt
apimaticcalculatorpythonv2.egg-info/requires.txt
apimaticcalculatorpythonv2.egg-info/top_level.txt
apimaticcalculatorpythonv2/controllers/__init__.py
apimaticcalculatorpythonv2/controllers/base_controller.py
apimaticcalculatorpythonv2/controllers/calculator_e_ps.py
apimaticcalculatorpythonv2/exceptions/__init__.py
apimaticcalculatorpythonv2/exceptions/api_exception.py
apimaticcalculatorpythonv2/http/__init__.py
apimaticcalculatorpythonv2/http/http_call_back.py
apimaticcalculatorpythonv2/http/http_client.py
apimaticcalculatorpythonv2/http/http_context.py
apimaticcalculatorpythonv2/http/http_method_enum.py
apimaticcalculatorpythonv2/http/http_request.py
apimaticcalculatorpythonv2/http/http_response.py
apimaticcalculatorpythonv2/http/requests_client.py
apimaticcalculatorpythonv2/models/__init__.py
apimaticcalculatorpythonv2/models/operation_type.py
tests/__init__.py
tests/http_response_catcher.py
tests/test_helper.py
tests/controllers/__init__.py
tests/controllers/controller_test_base.py
tests/controllers/test_calculator_e_ps.py